.gitlab-ci.yml
.travis.yml
CHANGES.rst
CONTRIBUTORS.rst
DEVELOP.rst
LICENSE.GPL
LICENSE.rst
MANIFEST.in
Makefile
README.rst
constraints.txt
constraints_plone43.txt
constraints_plone50.txt
constraints_plone51.txt
constraints_plone52.txt
requirements.txt
setup.cfg
setup.py
tox.ini
docs/conf.py
docs/index.rst
src/collective/__init__.py
src/collective.behavior.sdg.egg-info/PKG-INFO
src/collective.behavior.sdg.egg-info/SOURCES.txt
src/collective.behavior.sdg.egg-info/dependency_links.txt
src/collective.behavior.sdg.egg-info/entry_points.txt
src/collective.behavior.sdg.egg-info/namespace_packages.txt
src/collective.behavior.sdg.egg-info/not-zip-safe
src/collective.behavior.sdg.egg-info/requires.txt
src/collective.behavior.sdg.egg-info/top_level.txt
src/collective/behavior/__init__.py
src/collective/behavior/sdg/__init__.py
src/collective/behavior/sdg/configure.zcml
src/collective/behavior/sdg/interfaces.py
src/collective/behavior/sdg/permissions.zcml
src/collective/behavior/sdg/setuphandlers.py
src/collective/behavior/sdg/testing.py
src/collective/behavior/sdg/behaviors/__init__.py
src/collective/behavior/sdg/behaviors/configure.zcml
src/collective/behavior/sdg/behaviors/sustainable_development_goals.py
src/collective/behavior/sdg/browser/__init__.py
src/collective/behavior/sdg/browser/configure.zcml
src/collective/behavior/sdg/browser/overrides/.gitkeep
src/collective/behavior/sdg/browser/static/.gitkeep
src/collective/behavior/sdg/browser/static/sdg-01-nb.svg
src/collective/behavior/sdg/browser/static/sdg-02-nb.svg
src/collective/behavior/sdg/browser/static/sdg-03-nb.svg
src/collective/behavior/sdg/browser/static/sdg-04-nb.svg
src/collective/behavior/sdg/browser/static/sdg-05-nb.svg
src/collective/behavior/sdg/browser/static/sdg-06-nb.svg
src/collective/behavior/sdg/browser/static/sdg-07-nb.svg
src/collective/behavior/sdg/browser/static/sdg-08-nb.svg
src/collective/behavior/sdg/browser/static/sdg-09-nb.svg
src/collective/behavior/sdg/browser/static/sdg-10-nb.svg
src/collective/behavior/sdg/browser/static/sdg-11-nb.svg
src/collective/behavior/sdg/browser/static/sdg-12-nb.svg
src/collective/behavior/sdg/browser/static/sdg-13-nb.svg
src/collective/behavior/sdg/browser/static/sdg-14-nb.svg
src/collective/behavior/sdg/browser/static/sdg-15-nb.svg
src/collective/behavior/sdg/browser/static/sdg-16-nb.svg
src/collective/behavior/sdg/browser/static/sdg-17-nb.svg
