Metadata-Version: 2.1
Name: collective.behavior.sdg
Version: 1.0a1
Summary: Dexterity behavior to add a selection field of nato sustainable development goals
Home-page: https://github.com/collective/collective.behavior.sdg
Author: Stephan Geulette
Author-email: s.geulette@imio.be
License: GPL version 2
Project-URL: Source, https://github.com/collective/collective.behavior.sdg
Project-URL: Tracker, https://github.com/collective/collective.behavior.sdg/issues
Project-URL: PyPI, https://pypi.python.org/pypi/collective.behavior.sdg
Keywords: Python Plone
Platform: UNKNOWN
Classifier: Environment :: Web Environment
Classifier: Framework :: Plone
Classifier: Framework :: Plone :: Addon
Classifier: Framework :: Plone :: 4.3
Classifier: Programming Language :: Python
Classifier: Programming Language :: Python :: 2.7
Classifier: Operating System :: OS Independent
Classifier: License :: OSI Approved :: GNU General Public License v2 (GPLv2)
Requires-Python: ==2.7
Provides-Extra: test
